codeswitch/__init__.py
codeswitch/codeswitch.py
codeswitch-1.1.dist-info/LICENSE
codeswitch-1.1.dist-info/METADATA
codeswitch-1.1.dist-info/WHEEL
codeswitch-1.1.dist-info/top_level.txt
codeswitch-1.1.dist-info/RECORD
