Metadata-Version: 2.1
Name: codeswitch
Version: 1.1
Summary: Code Switch is a NLP tool can use for language identification, pos tagging, name entity recognition, sentiment analysis of code mixed data.
Home-page: https://github.com/sagorbrur/codeswitch
Author: Sagor Sarker
Author-email: sagorhem3532@gmail.com
License: MIT
Platform: UNKNOWN
Classifier: Programming Language :: Python :: 3
Classifier: License :: OSI Approved :: MIT License
Classifier: Operating System :: OS Independent
Requires-Python: >=3.5
Requires-Dist: transformers
